LICENSE
README.md
setup.py
cronwhen/__init__.py
cronwhen/cronwhen.py
cronwhen.egg-info/PKG-INFO
cronwhen.egg-info/SOURCES.txt
cronwhen.egg-info/dependency_links.txt
cronwhen.egg-info/top_level.txt
test/test_cronwhen.py